whid/__init__.py
whid/__main__.py
whid/utils.py
whid-0.1.2.dist-info/LICENSE
whid-0.1.2.dist-info/METADATA
whid-0.1.2.dist-info/WHEEL
whid-0.1.2.dist-info/entry_points.txt
whid-0.1.2.dist-info/top_level.txt
whid-0.1.2.dist-info/RECORD
