Metadata-Version: 2.1
Name: whid
Version: 0.1.2
Summary: What Have I Done? - Review things you have done on your desktop.
Home-page: https://github.com/git-akihakune/whid
Author: akihakune
Author-email: akihakune@gmail.com
License: MIT
Keywords: whid what have i done
Platform: UNKNOWN
Classifier: Development Status :: 5 - Production/Stable
Classifier: Environment :: Console
Classifier: Intended Audience :: End Users/Desktop
Classifier: License :: OSI Approved :: MIT License
Classifier: Natural Language :: English
Classifier: Programming Language :: Python :: 3.9
Classifier: Topic :: Utilities
Requires-Python: >=3.6
Requires-Dist: argparse
Requires-Dist: moviepy
Requires-Dist: plyer
Requires-Dist: pyautogui
Requires-Dist: tqdm
